eth_common/__init__.py
eth_common/types.py
eth_common/resources/version
eth_common-0.0.5.dist-info/LICENSE
eth_common-0.0.5.dist-info/METADATA
eth_common-0.0.5.dist-info/WHEEL
eth_common-0.0.5.dist-info/top_level.txt
eth_common-0.0.5.dist-info/RECORD
